nonebot_plugin_drawer/__init__.py
nonebot_plugin_drawer/config.py
nonebot_plugin_drawer/drawer.py
nonebot_plugin_drawer/limiter.py
nonebot_plugin_drawer-0.4.0.dist-info/LICENSE
nonebot_plugin_drawer-0.4.0.dist-info/WHEEL
nonebot_plugin_drawer-0.4.0.dist-info/METADATA
nonebot_plugin_drawer-0.4.0.dist-info/RECORD
